pymojihash/__init__.py
pymojihash/emojis.json
pymojihash/pymojihash.py
pymojihash-0.3.0.dist-info/METADATA
pymojihash-0.3.0.dist-info/RECORD
pymojihash-0.3.0.dist-info/WHEEL
pymojihash-0.3.0.dist-info/top_level.txt
