Metadata-Version: 2.1
Name: pymojihash
Version: 0.3.0
Summary: Python 3 package for hashing strings to emojis.
Home-page: UNKNOWN
Author: Lily FYI
Author-email: hello@lily.fyi
License: UNKNOWN
Platform: UNKNOWN
